{
  "schemaVersion": "1.0",
  "generatedAt": "2026-07-20T18:31:28.0613406\u002B00:00",
  "trips": [
    {
      "publicId": "0b81404b-6159-4065-b4b6-2ea271dc6839",
      "slug": "polsko-balt-aktivni-tyden-v-jastrzebie-gore-2026-07-0b8140",
      "title": "Polsko-Balt \u2013 aktivn\u00ED t\u00FDden v Jastrz\u0119bie G\u00F3\u0159e",
      "subtitle": "Jastrz\u0119bia G\u00F3ra",
      "dateFrom": "2026-07-27",
      "dateTo": "2026-08-03",
      "countryCode": "PL",
      "coverImageUrl": null,
      "status": "upcoming",
      "isListed": false,
      "revision": 1,
      "updatedAt": "2026-07-20T18:31:28.0613406\u002B00:00",
      "vaultAvailable": false
    },
    {
      "publicId": "a386ffa5-76fa-43f6-bdf1-e58468f30d7d",
      "slug": "polsko-balt-aktivni-tyden-v-jastrzebie-gore-2026-07-a386ff",
      "title": "Polsko-Balt \u2013 aktivn\u00ED t\u00FDden v Jastrz\u0119bie G\u00F3\u0159e-v2",
      "subtitle": "Jastrz\u0119bia G\u00F3ra",
      "dateFrom": "2026-07-27",
      "dateTo": "2026-08-03",
      "countryCode": "PL",
      "coverImageUrl": null,
      "status": "upcoming",
      "isListed": true,
      "revision": 1,
      "updatedAt": "2026-07-20T04:06:42.1009669\u002B00:00",
      "vaultAvailable": false
    }
  ]
}